{"schemaVersion":"1.0","appDefinitionTemplate":{"id":"/providers/Microsoft.PowerApps/apps/","type":"Microsoft.PowerApps/apps","tags":{"primaryDeviceWidth":"1366","primaryDeviceHeight":"768","sienaVersion":"20210427T173403Z-3.21031.49.0","deviceCapabilities":"","supportsPortrait":"false","supportsLandscape":"true","primaryFormFactor":"Tablet","publisherVersion":"3.21031.49","minimumRequiredApiVersion":"2.2.0","hasComponent":"false","hasUnlockedComponent":"false","isUnifiedRootApp":"false"},"properties":{"appVersion":"2021-04-27T17:34:03Z","lifeCycleId":"Published","createdByClientVersion":{"major":3,"minor":21031,"build":49,"revision":0,"majorRevision":0,"minorRevision":0},"minClientVersion":{"major":3,"minor":21031,"build":49,"revision":0,"majorRevision":0,"minorRevision":0},"backgroundColor":"rgba(0, 176, 240, 1)","backgroundImageUri":"/1748887897759332532/Ncc194bdd-88f5-4873-932f-016838e05372-logoSmallFile","displayName":"Data lake catalogs DEV","description":"","commitMessage":"","appUris":{"documentUri":{"value":"/1748887897759332532/N8d591ec5-43d9-4b03-89d8-5728fbbcb1c2-document.msapp"},"imageUris":[]},"createdTime":"0001-01-01T00:00:00Z","lastModifiedTime":"0001-01-01T00:00:00Z","sharedGroupsCount":0,"sharedUsersCount":0,"icons":{"smallIconUri":"/1748887897759332532/Na9c9ea47-f27d-4e04-9ef0-a4c9f01ef9d3-small.png","mediumIconUri":"/1748887897759332532/N58bb0301-9043-4457-99f9-01d1a49ad95e-medium.png","largeIconUri":"/1748887897759332532/N121c4afe-6439-4696-a92e-a6c233d385e9-large.png","wideIconUri":"/1748887897759332532/N1b87ddcb-179b-4af9-810f-b1c33e6d2dc1-wide.png"},"connectionReferences":{"cd6f39fd-1d94-40a2-9598-a779db4197b4":{"id":"ad548e13-be0a-485f-9e22-6250e920351e","displayName":"SQL Server","iconUri":"https://connectoricons-prod.azureedge.net/releases/v1.0.1460/1.0.1460.2389/sql/icon.png","dataSources":["[mdm_control].[flavor_catalog]","[mdm_control].[product_catalog]","[lars].[dim_product]"],"dependencies":[],"dependents":["ddb864f1-179d-4c81-8370-cbf4931596eb","0c6fb001-4c2c-40a8-bd9e-cd70a8ba3063","14e6629d-48f8-4e15-a0e3-2d8f1aaeb2ac"],"parameterHints":{},"isOnPremiseConnection":false,"sharedConnectionId":"8938082d-5891-4676-b2d3-f10450c2c712","bypassConsent":false,"dataSets":{"asq-tccc-dms01-lad-dev-use2.database.windows.net,Lars":{"dataSources":{"[mdm_control].[flavor_catalog]":{"tableName":"[mdm_control].[flavor_catalog]"},"[mdm_control].[product_catalog]":{"tableName":"[mdm_control].[product_catalog]"},"[lars].[dim_product]":{"tableName":"[lars].[dim_product]"}}}},"apiTier":"Premium","isCustomApiConnection":false,"authenticationType":"sqlAuthentication","endpoints":["asq-tccc-dms01-lad-dev-use2.database.windows.net,Lars"]},"ddb864f1-179d-4c81-8370-cbf4931596eb":{"id":"006fea04-a575-4304-ab5e-9275cf3ef93c","displayName":"Logic flows","iconUri":"https://connectoricons-prod.azureedge.net/releases/v1.0.1438/1.0.1438.2324/logicflows/icon.png","dataSources":["FlavorCatalog"],"dependencies":["cd6f39fd-1d94-40a2-9598-a779db4197b4"],"dependents":[],"parameterHints":{"workflowName":{"value":"90ae9777-90e0-40f0-9885-19d06305c766"},"cd6f39fd-1d94-40a2-9598-a779db4197b4":{"value":"shared_sql"}},"isOnPremiseConnection":false,"bypassConsent":false,"dataSets":{},"apiTier":"Standard","isCustomApiConnection":false,"actions":["Run"]},"0c6fb001-4c2c-40a8-bd9e-cd70a8ba3063":{"id":"006fea04-a575-4304-ab5e-9275cf3ef93c","displayName":"Logic flows","iconUri":"https://connectoricons-prod.azureedge.net/releases/v1.0.1438/1.0.1438.2324/logicflows/icon.png","dataSources":["FlavorEdit"],"dependencies":["cd6f39fd-1d94-40a2-9598-a779db4197b4"],"dependents":[],"parameterHints":{"workflowName":{"value":"a924f5be-80bf-4fe1-a4a2-7f9df57d466b"},"workflowEntityId":{},"cd6f39fd-1d94-40a2-9598-a779db4197b4":{"value":"shared_sql"}},"isOnPremiseConnection":false,"bypassConsent":false,"dataSets":{},"apiTier":"Standard","isCustomApiConnection":false,"actions":["Run"]},"14e6629d-48f8-4e15-a0e3-2d8f1aaeb2ac":{"id":"006fea04-a575-4304-ab5e-9275cf3ef93c","displayName":"Logic flows","iconUri":"https://connectoricons-prod.azureedge.net/releases/v1.0.1438/1.0.1438.2324/logicflows/icon.png","dataSources":["ProductEdit"],"dependencies":["cd6f39fd-1d94-40a2-9598-a779db4197b4"],"dependents":[],"parameterHints":{"workflowName":{"value":"31897bf5-aac1-40a0-aef6-ea684991fe42"},"workflowEntityId":{},"cd6f39fd-1d94-40a2-9598-a779db4197b4":{"value":"shared_sql"}},"isOnPremiseConnection":false,"bypassConsent":false,"dataSets":{},"apiTier":"Standard","isCustomApiConnection":false,"actions":["Run"]}},"databaseReferences":{},"almMode":"Environment","performanceOptimizationEnabled":true,"canConsumeAppPass":true,"executionRestrictions":{"isTeamsOnly":false,"dataLossPreventionEvaluationResult":{"status":"Compliant","lastEvaluationDate":"2021-03-16T23:06:01.7691146Z","violationDetails":[]}}},"isAppComponentLibrary":false,"appType":"ClassicCanvasApp","appComponents":[]}}